{
	"configurations" : 
	[
		{
			"directories" : 
			[
				{
					"build" : ".",
					"jsonFile" : "directory-.-f5ebdc15457944623624.json",
					"minimumCMakeVersion" : 
					{
						"string" : "3.16.0"
					},
					"projectIndex" : 0,
					"source" : ".",
					"targetIndexes" : 
					[
						0,
						1
					]
				}
			],
			"name" : "",
			"projects" : 
			[
				{
					"directoryIndexes" : 
					[
						0
					],
					"name" : "ComSpen",
					"targetIndexes" : 
					[
						0,
						1
					]
				}
			],
			"targets" : 
			[
				{
					"directoryIndex" : 0,
					"id" : "ComSpen::@6890427a1f51a3e7e1df",
					"jsonFile" : "target-ComSpen-e21738a9d34f782fe16b.json",
					"name" : "ComSpen",
					"projectIndex" : 0
				},
				{
					"directoryIndex" : 0,
					"id" : "smt2z3::@6890427a1f51a3e7e1df",
					"jsonFile" : "target-smt2z3-68a8c50359954f5eaf91.json",
					"name" : "smt2z3",
					"projectIndex" : 0
				}
			]
		}
	],
	"kind" : "codemodel",
	"paths" : 
	{
		"build" : "/home/zhuyt/ComSpen/build",
		"source" : "/home/zhuyt/ComSpen"
	},
	"version" : 
	{
		"major" : 2,
		"minor" : 4
	}
}
